demos/exp3/top.v

module top(
	input a,
	input b,
	output f
);

	assign f = a^b;
endmodule

demos/exp3/obj_dir/simx.vcd
$version Generated by VerilatedVcd $end
$date Wed Feb 23 16:32:27 2022 $end
$timescale 1ps $end

 $scope module TOP $end
  $var wire  1 # a $end
  $var wire  1 $ b $end
  $var wire  1 % f $end
  $scope module top $end
   $var wire  1 # a $end
   $var wire  1 $ b $end
   $var wire  1 % f $end
  $upscope $end
 $upscope $end
$enddefinitions $end


#1
1#
0$
1%
#2
1$
0%
#3
#4
0#
0$
#5
1#
1$
#6
0#
1%
#7
#8
1#
0$
#9
0#
0%
#10
#11
1#
1%
#12
1$
0%
#13
0#
0$
#14
1$
1%
#15
1#
0%
#16
0$
1%
#17
0#
0%
#18
1#
1$
#19
0$
1%
#20
#21
1$
0%
#22
#23
0#
1%
#24
0$
0%
#25
1#
1%
#26
#27
#28
0#
1$
#29
0$
0%
#30
1$
1%
#31
1#
0%
#32
0#
1%
#33
#34
#35
1#
0%
#36
0#
1%
#37
#38
#39
0$
0%
#40
1#
1%
#41
#42
0#
0%
#43
#44
1#
1$
#45
0#
1%
#46
0$
0%
#47
#48
1#
1%
#49
0#
0%
#50
1$
1%
#51
1#
0$
#52
0#
0%
#53
1#
1$
#54
0$
1%
#55
#56
0#
0%
#57
1#
1%
#58
0#
1$
#59
1#
0%
#60
0#
1%
#61
#62
1#
0%
#63
#64
#65
#66
0$
1%
#67
1$
0%
#68
0#
1%
#69
#70
1#
0$
#71
0#
1$
#72
#73
1#
0%
#74
0#
0$
#75
1$
1%
#76
#77
#78
#79
#80
1#
0%
#81
0$
1%
#82
0#
0%
#83
1#
1%
#84
#85
0#
0%
#86
#87
1#
1%
#88
1$
0%
#89
#90
0$
1%
#91
0#
1$
#92
1#
0$
#93
1$
0%
#94
0#
1%
#95
#96
1#
0%
#97
#98
0#
0$
#99
1#
1$
#100
0#
1%
#101
0$
0%
#102
1#
1$
#103
0$
1%
#104
0#
0%
#105
#106
#107
1#
1$
#108
0$
1%
#109
0#
1$
#110
#111
#112
#113
0$
0%
#114
1#
1$
#115
0#
0$
#116
1#
1%
#117
0#
0%
#118
1#
1$
#119
0$
1%
#120
0#
1$
#121
0$
0%
#122
1#
1$
#123
0#
0$
#124
#125
1#
1%
#126
1$
0%
#127
0$
1%
#128
0#
1$
#129
0$
0%
#130
#131
1$
1%
#132
0$
0%
#133
#134
1$
1%
#135
0$
0%
#136
#137
1$
1%
#138
1#
0$
#139
0#
1$
#140
1#
0%
#141
0$
1%
#142
#143
0#
1$
#144
1#
0%
#145
0$
1%
#146
1$
0%
#147
0$
1%
#148
0#
1$
#149
0$
0%
#150
#151
#152
#153
1$
1%
#154
1#
0$
#155
#156
#157
0#
0%
#158
1#
1$
#159
0#
0$
#160
1$
1%
#161
#162
1#
0$
#163
1$
0%
#164
#165
0$
1%
#166
1$
0%
#167
0#
1%
#168
1#
0$
#169
#170
0#
0%
#171
#172
1$
1%
#173
#174
0$
0%
#175
#176
#177
1#
1$
#178
0#
1%
#179
0$
0%
#180
1$
1%
#181
0$
0%
#182
#183
1#
1$
#184
0$
1%
#185
0#
1$
#186
0$
0%
#187
1#
1$
#188
0$
1%
#189
0#
1$
#190
0$
0%
#191
1#
1%
#192
1$
0%
#193
#194
0#
1%
#195
1#
0$
#196
0#
1$
#197
0$
0%
#198
#199
1$
1%
#200
0$
0%
#201
1$
1%
#202
0$
0%
#203
#204
#205
1#
1%
#206
1$
0%
#207
0$
1%
#208
0#
0%
#209
1#
1%
#210
0#
1$
#211
0$
0%
#212
1$
1%
#213
1#
0$
#214
1$
0%
#215
#216
0$
1%
#217
0#
1$
#218
0$
0%
#219
1#
1%
#220
1$
0%
#221
0#
0$
#222
1$
1%
#223
0$
0%
#224
1$
1%
#225
0$
0%
#226
#227
1$
1%
#228
1#
0%
#229
0$
1%
#230
0#
1$
#231
#232
1#
0$
#233
1$
0%
#234
0$
1%
#235
#236
1$
0%
#237
0#
1%
#238
1#
0$
#239
1$
0%
#240
#241
0$
1%
#242
0#
1$
#243
1#
0%
#244
0$
1%
#245
0#
1$
#246
1#
0$
#247
#248
0#
0%
#249
1#
1$
#250
0#
0$
#251
1#
1%
#252
0#
1$
#253
1#
0%
#254
#255
0#
1%
#256
#257
1#
0$
#258
0#
0%
#259
1$
1%
#260
0$
0%
#261
1#
1%
#262
0#
0%
#263
#264
#265
#266
1$
1%
#267
0$
0%
#268
1#
1%
#269
#270
1$
0%
#271
#272
0#
0$
#273
1$
1%
#274
0$
0%
#275
1$
1%
#276
#277
1#
0$
#278
1$
0%
#279
0#
1%
#280
1#
0$
#281
0#
0%
#282
#283
1$
1%
#284
0$
0%
#285
1#
1$
#286
#287
0$
1%
#288
1$
0%
#289
0$
1%
#290
1$
0%
#291
#292
0$
1%
#293
#294
1$
0%
#295
0#
1%
#296
0$
0%
#297
1#
1%
#298
0#
1$
#299
1#
0%
#300
0$
1%
#301
0#
1$
#302
1#
0%
#303
#304
0#
0$
#305
1#
1$
#306
0$
1%
#307
0#
0%
#308
1$
1%
#309
1#
0%
#310
#311
0#
1%
#312
1#
0%
#313
#314
0$
1%
#315
0#
0%
#316
1$
1%
#317
1#
0$
#318
0#
0%
#319
1#
1$
#320
0#
0$
#321
#322
1$
1%
#323
0$
0%
#324
1$
1%
#325
1#
0%
#326
0#
0$
#327
1$
1%
#328
1#
0%
#329
0$
1%
#330
1$
0%
#331
0$
1%
#332
0#
0%
#333
1$
1%
#334
1#
0%
#335
0#
1%
#336
1#
0$
#337
1$
0%
#338
0$
1%
#339
#340
#341
#342
0#
0%
#343
1#
1%
#344
#345
0#
1$
#346
#347
1#
0$
#348
0#
1$
#349
1#
0%
#350
0#
1%
#351
#352
0$
0%
#353
1$
1%
#354
#355
1#
0%
#356
#357
0$
1%
#358
1$
0%
#359
0#
0$
#360
1#
1%
#361
1$
0%
#362
0#
0$
#363
#364
1#
1$
#365
#366
#367
0#
1%
#368
1#
0$
#369
0#
1$
#370
1#
0$
#371
1$
0%
#372
0$
1%
#373
#374
1$
0%
#375
0#
1%
#376
1#
0$
#377
0#
1$
#378
0$
0%
#379
1#
1%
#380
0#
0%
#381
1#
1$
#382
0#
0$
#383
1$
1%
#384
0$
0%
#385
1#
1%
#386
0#
0%
#387
1#
1$
#388
0#
0$
#389
1#
1%
#390
#391
#392
0#
1$
#393
0$
0%
#394
1$
1%
#395
0$
0%
#396
#397
1#
1%
#398
0#
1$
#399
1#
0$
#400
#401
0#
0%
#402
1$
1%
#403
1#
0%
#404
#405
0$
1%
#406
#407
1$
0%
#408
#409
#410
0#
0$
#411
1#
1%
#412
0#
0%
#413
#414
1#
1%
#415
0#
1$
#416
#417
1#
0%
#418
0#
0$
#419
#420
1#
1$
#421
0#
0$
#422
1#
1$
#423
0$
1%
#424
0#
1$
#425
#426
1#
0%
#427
#428
0#
0$
#429
1#
1$
#430
0#
1%
#431
0$
0%
#432
1$
1%
#433
1#
0%
#434
0#
1%
#435
1#
0%
#436
0#
1%
#437
#438
1#
0%
#439
0#
1%
#440
0$
0%
#441
1$
1%
#442
1#
0$
#443
0#
1$
#444
#445
1#
0$
#446
1$
0%
#447
0#
1%
#448
1#
0$
#449
0#
1$
#450
1#
0%
#451
0#
0$
#452
1#
1%
#453
#454
0#
1$
#455
1#
0$
#456
#457
0#
1$
#458
0$
0%
#459
#460
1$
1%
#461
#462
1#
0$
#463
0#
0%
#464
1$
1%
#465
1#
0$
#466
0#
1$
#467
#468
#469
1#
0$
#470
1$
0%
#471
0#
0$
#472
1#
1%
#473
1$
0%
#474
0$
1%
#475
1$
0%
#476
#477
0#
0$
#478
1#
1%
#479
0#
0%
#480
1#
1$
#481
0#
0$
#482
1#
1%
#483
1$
0%
#484
#485
0$
1%
#486
0#
1$
#487
1#
0%
#488
0#
0$
#489
1$
1%
#490
#491
0$
0%
#492
#493
1$
1%
#494
#495
1#
0$
#496
0#
1$
#497
#498
1#
0%
#499
0#
1%
#500
#501
1#
0$
#502
#503
1$
0%
#504
#505
0#
1%
#506
0$
0%
#507
1#
1%
#508
0#
0%
#509
#510
1#
1$
#511
0#
1%
#512
1#
0$
#513
#514
0#
1$
#515
1#
0$
#516
1$
0%
#517
0$
1%
#518
#519
#520
0#
1$
#521
0$
0%
#522
1#
1$
#523
#524
#525
0$
1%
#526
0#
0%
#527
1$
1%
#528
#529
0$
0%
#530
1$
1%
#531
1#
0%
#532
0#
0$
#533
1#
1%
#534
0#
0%
#535
#536
1#
1%
#537
#538
0#
0%
#539
1#
1$
#540
#541
0#
1%
#542
1#
0$
#543
1$
0%
#544
#545
0#
1%
#546
#547
1#
0%
#548
0$
1%
#549
1$
0%
#550
#551
0#
0$
#552
1$
1%
#553
1#
0$
#554
#555
#556
1$
0%
#557
0$
1%
#558
#559
0#
0%
#560
1#
1%
#561
0#
0%
#562
1#
1$
#563
0$
1%
#564
#565
#566
1$
0%
#567
#568
0#
0$
#569
1#
1$
#570
0#
1%
#571
1#
0$
#572
0#
1$
#573
0$
0%
#574
1#
1%
#575
0#
1$
#576
0$
0%
#577
1#
1$
#578
0$
1%
#579
1$
0%
#580
0#
1%
#581
1#
0%
#582
0#
0$
#583
1#
1$
#584
0#
0$
#585
1$
1%
#586
1#
0$
#587
#588
1$
0%
#589
0#
0$
#590
#591
1#
1%
#592
#593
0#
0%
#594
1$
1%
#595
1#
0$
#596
0#
1$
#597
#598
1#
0%
#599
0#
0$
#600
1#
1%
#601
1$
0%
#602
0#
0$
#603
1#
1$
#604
#605
0#
1%
#606
1#
0%
#607
0#
0$
#608
#609
1#
1%
#610
#611
#612
1$
0%
#613
#614
0#
1%
#615
1#
0%
#616
0$
1%
#617
0#
0%
#618
1$
1%
#619
1#
0%
#620
0#
1%
#621
1#
0$
#622
1$
0%
#623
0#
1%
#624
1#
0%
#625
0$
1%
#626
0#
0%
#627
1$
1%
#628
1#
0%
#629
0#
1%
#630
#631
1#
0$
#632
1$
0%
#633
0#
1%
#634
1#
0%
#635
#636
0$
1%
#637
#638
#639
#640
#641
0#
1$
#642
1#
0%
#643
0$
1%
#644
0#
1$
#645
#646
1#
0%
#647
0$
1%
#648
0#
1$
#649
#650
#651
1#
0%
#652
0$
1%
#653
#654
0#
0%
#655
#656
1#
1%
#657
#658
#659
0#
0%
#660
#661
1#
1$
#662
0$
1%
#663
#664
1$
0%
#665
#666
0#
0$
#667
1#
1$
#668
0$
1%
#669
1$
0%
#670
#671
0$
1%
#672
0#
1$
#673
#674
1#
0$
#675
1$
0%
#676
0$
1%
#677
0#
0%
#678
#679
1$
1%
#680
1#
0$
#681
#682
0#
0%
#683
1#
1$
#684
0#
1%
#685
1#
0%
#686
0#
0$
#687
1#
1%
#688
1$
0%
#689
0#
1%
#690
#691
#692
#693
1#
0$
#694
#695
0#
0%
#696
1$
1%
#697
0$
0%
#698
1#
1%
#699
0#
1$
#700
1#
0%
#701
#702
0$
1%
#703
0#
1$
#704
0$
0%
#705
#706
1#
1%
#707
1$
0%
#708
0$
1%
#709
0#
0%
#710
#711
1#
1%
#712
1$
0%
#713
0$
1%
#714
1$
0%
#715
0$
1%
#716
0#
0%
#717
1$
1%
#718
1#
0$
#719
0#
1$
#720
0$
0%
#721
1#
1$
#722
0$
1%
#723
#724
0#
1$
#725
1#
0%
#726
0$
1%
#727
#728
#729
0#
1$
#730
1#
0%
#731
#732
0#
1%
#733
1#
0%
#734
#735
0#
1%
#736
#737
1#
0%
#738
0$
1%
#739
1$
0%
#740
0$
1%
#741
0#
0%
#742
#743
#744
#745
1#
1%
#746
#747
1$
0%
#748
0#
0$
#749
1$
1%
#750
0$
0%
#751
1#
1%
#752
#753
#754
0#
0%
#755
1$
1%
#756
1#
0$
#757
1$
0%
#758
0#
1%
#759
1#
0%
#760
0$
1%
#761
#762
#763
0#
1$
#764
1#
0$
#765
0#
1$
#766
1#
0%
#767
0$
1%
#768
#769
1$
0%
#770
0#
1%
#771
#772
1#
0%
#773
0$
1%
#774
0#
0%
#775
1#
1$
#776
0$
1%
#777
0#
0%
#778
#779
1#
1$
#780
0#
1%
#781
#782
1#
0%
#783
0#
0$
#784
1#
1$
#785
0#
0$
#786
#787
1#
1$
#788
0#
0$
#789
1#
1%
#790
#791
0#
0%
#792
#793
1$
1%
#794
#795
0$
0%
#796
1$
1%
#797
#798
0$
0%
#799
#800
1#
1%
#801
0#
1$
#802
#803
0$
0%
#804
#805
1#
1$
#806
0#
1%
#807
1#
0%
#808
#809
0#
1%
#810
0$
0%
#811
1#
1%
#812
1$
0%
#813
0#
0$
#814
1#
1%
#815
0#
0%
#816
#817
1#
1%
#818
#819
1$
0%
#820
0#
0$
#821
#822
1#
1$
#823
0$
1%
#824
0#
1$
#825
1#
0$
#826
0#
0%
#827
1#
1$
#828
0#
1%
#829
1#
0%
#830
#831
0#
1%
#832
1#
0%
#833
#834
0$
1%
#835
0#
1$
#836
#837
#838
#839
1#
0%
#840
0$
1%
#841
1$
0%
#842
0$
1%
#843
0#
1$
#844
1#
0$
#845
0#
0%
#846
1#
1%
#847
1$
0%
#848
0#
1%
#849
#850
1#
0$
#851
#852
1$
0%
#853
0$
1%
#854
0#
1$
#855
1#
0%
#856
0$
1%
#857
0#
0%
#858
1#
1$
#859
0$
1%
#860
#861
#862
0#
0%
#863
1#
1%
#864
1$
0%
#865
0#
1%
#866
#867
1#
0%
#868
0#
0$
#869
1#
1%
#870
#871
0#
1$
#872
1#
0$
#873
#874
1$
0%
#875
0#
0$
#876
1#
1$
#877
#878
0#
0$
#879
1$
1%
#880
0$
0%
#881
#882
1#
1$
#883
#884
0#
1%
#885
1#
0%
#886
#887
0#
0$
#888
#889
1$
1%
#890
1#
0%
#891
0#
0$
#892
1$
1%
#893
1#
0$
#894
1$
0%
#895
0#
1%
#896
1#
0$
#897
#898
0#
1$
#899
1#
0$
#900
0#
1$
#901
1#
0%
#902
0#
0$
#903
#904
#905
1$
1%
#906
1#
0$
#907
#908
#909
0#
0%
#910
#911
1$
1%
#912
1#
0%
#913
0#
1%
#914
#915
1#
0$
#916
0#
0%
#917
1$
1%
#918
0$
0%
#919
1#
1%
#920
0#
1$
#921
1#
0$
#922
#923
0#
0%
#924
1#
1%
#925
1$
0%
#926
#927
0#
0$
#928
#929
1#
1$
#930
0#
0$
#931
1#
1%
#932
0#
1$
#933
1#
0%
#934
#935
0$
1%
#936
0#
1$
#937
0$
0%
#938
1#
1%
#939
0#
0%
#940
1$
1%
#941
1#
0%
#942
0#
0$
#943
1#
1$
#944
0#
0$
#945
#946
1$
1%
#947
1#
0%
#948
0$
1%
#949
0#
0%
#950
1#
1$
#951
0#
0$
#952
#953
#954
#955
1$
1%
#956
0$
0%
#957
#958
#959
1#
1%
#960
0#
1$
#961
1#
0%
#962
0$
1%
#963
0#
0%
#964
#965
#966
1#
1$
#967
0#
0$
#968
1#
1%
#969
0#
0%
#970
#971
1#
1%
#972
0#
1$
#973
1#
0$
#974
#975
#976
0#
0%
#977
1#
1$
#978
0#
1%
#979
1#
0$
#980
1$
0%
#981
0#
0$
#982
#983
#984
#985
1$
1%
#986
1#
0%
#987
#988
0#
0$
#989
#990
1#
1$
#991
0#
1%
#992
1#
0%
#993
0#
1%
#994
#995
1#
0%
#996
0#
0$
#997
1#
1$
#998
0#
0$
#999
1#
1$
#1000
0#
1%
#1001
#1002
#1003
1#
0$
#1004
0#
1$
#1005
#1006
0$
0%
#1007
1$
1%
#1008
1#
0$
#1009
0#
1$
#1010
1#
0%
#1011
0#
1%
#1012
1#
0$
#1013
0#
0%
#1014
1$
1%
#1015
1#
0$
#1016
0#
1$
#1017
0$
0%
#1018
1$
1%
#1019
1#
0$
#1020
0#
1$
#1021
1#
0$
#1022
0#
1$
#1023
1#
0%
#1024
#1025
0$
1%
#1026
0#
1$
#1027
0$
0%
#1028
1#
1%
#1029
0#
1$
#1030
#1031
0$
0%
#1032
#1033
1#
1%
#1034
#1035
1$
0%
#1036
0$
1%
#1037
1$
0%
#1038
0#
0$
#1039
1#
1$
#1040
0$
1%
#1041
0#
1$
#1042
1#
0$
#1043
1$
0%
#1044
0#
1%
#1045
0$
0%
#1046
#1047
1#
1%
#1048
0#
0%
#1049
1#
1$
#1050
0#
0$
#1051
1$
1%
#1052
#1053
1#
0$
#1054
#1055
0#
0%
#1056
#1057
1$
1%
#1058
#1059
0$
0%
#1060
1#
1$
#1061
#1062
0$
1%
#1063
0#
0%
#1064
1$
1%
#1065
1#
0$
#1066
#1067
1$
0%
#1068
0$
1%
#1069
0#
1$
#1070
0$
0%
#1071
1#
1%
#1072
0#
1$
#1073
0$
0%
#1074
1#
1%
#1075
0#
0%
#1076
1#
1$
#1077
#1078
#1079
#1080
0#
0$
#1081
1#
1$
#1082
0#
1%
#1083
1#
0$
#1084
1$
0%
#1085
0$
1%
#1086
#1087
0#
1$
#1088
0$
0%
#1089
1#
1$
#1090
#1091
0$
1%
#1092
#1093
#1094
0#
0%
#1095
#1096
1#
1$
#1097
0#
1%
#1098
#1099
1#
0$
#1100
0#
0%
#1101
1$
1%
#1102
1#
0$
#1103
0#
1$
#1104
1#
0%
#1105
0#
0$
#1106
1$
1%
#1107
#1108
1#
0$
#1109
0#
1$
#1110
0$
0%
#1111
1$
1%
#1112
1#
0$
#1113
#1114
#1115
0#
1$
#1116
1#
0$
#1117
0#
0%
#1118
#1119
1#
1$
#1120
#1121
#1122
0#
0$
#1123
1#
1$
#1124
0#
1%
#1125
1#
0$
#1126
1$
0%
#1127
0#
0$
#1128
1#
1$
#1129
0#
0$
#1130
1#
1%
#1131
#1132
0#
1$
#1133
#1134
1#
0%
#1135
0#
0$
#1136
#1137
1#
1%
#1138
0#
0%
#1139
#1140
1#
1$
#1141
0#
0$
#1142
#1143
1#
1$
#1144
#1145
#1146
0#
0$
#1147
1#
1%
#1148
#1149
#1150
#1151
0#
0%
#1152
1$
1%
#1153
0$
0%
#1154
#1155
1$
1%
#1156
1#
0$
#1157
0#
1$
#1158
1#
0%
#1159
0#
0$
#1160
1$
1%
#1161
1#
0$
#1162
1$
0%
#1163
0$
1%
#1164
#1165
0#
0%
#1166
#1167
#1168
1$
1%
#1169
0$
0%
#1170
1#
1%
#1171
1$
0%
#1172
#1173
0#
0$
#1174
1$
1%
#1175
#1176
0$
0%
#1177
1#
1%
#1178
#1179
0#
0%
#1180
1#
1$
#1181
0#
1%
#1182
1#
0%
#1183
0#
1%
#1184
0$
0%
#1185
1#
1$
#1186
#1187
0#
0$
#1188
1$
1%
#1189
#1190
0$
0%
#1191
#1192
1$
1%
#1193
#1194
#1195
1#
0%
#1196
0#
0$
#1197
1$
1%
#1198
1#
0$
#1199
1$
0%
#1200
0$
1%
#1201
0#
0%
#1202
1#
1$
#1203
0#
0$
#1204
#1205
1#
1%
#1206
0#
1$
#1207
#1208
#1209
0$
0%
#1210
#1211
1#
1%
#1212
0#
0%
#1213
1#
1$
#1214
0#
0$
#1215
1$
1%
#1216
1#
0$
#1217
#1218
1$
0%
#1219
0#
1%
#1220
1#
0%
#1221
0$
1%
#1222
0#
0%
#1223
1#
1$
#1224
#1225
#1226
#1227
#1228
0$
1%
#1229
0#
1$
#1230
1#
0$
#1231
#1232
#1233
0#
0%
#1234
1$
1%
#1235
#1236
#1237
1#
0%
#1238
0$
1%
#1239
0#
0%
#1240
1$
1%
#1241
1#
0%
#1242
0#
0$
#1243
1#
1$
#1244
#1245
0$
1%
#1246
0#
0%
#1247
1$
1%
#1248
0$
0%
#1249
1#
1%
#1250
1$
0%
#1251
0#
0$
#1252
1#
1$
#1253
0$
1%
#1254
0#
1$
#1255
1#
0$
#1256
0#
0%
#1257
1#
1$
#1258
0$
1%
#1259
0#
0%
#1260
1$
1%
#1261
0$
0%
#1262
1#
1%
#1263
#1264
0#
0%
#1265
#1266
#1267
1$
1%
#1268
#1269
1#
0$
#1270
0#
0%
#1271
#1272
1#
1$
#1273
0$
1%
#1274
0#
0%
#1275
#1276
1#
1%
#1277
0#
1$
#1278
#1279
1#
0$
#1280
1$
0%
#1281
0#
1%
#1282
0$
0%
#1283
#1284
1#
1%
#1285
0#
1$
#1286
0$
0%
#1287
1$
1%
#1288
1#
0%
#1289
#1290
#1291
#1292
#1293
0#
1%
#1294
#1295
0$
0%
#1296
#1297
1#
1%
#1298
#1299
0#
0%
#1300
#1301
#1302
#1303
#1304
1#
1$
#1305
#1306
#1307
0#
0$
#1308
#1309
1$
1%
#1310
1#
0$
#1311
1$
0%
#1312
0#
0$
#1313
1$
1%
#1314
0$
0%
#1315
#1316
1#
1%
#1317
1$
0%
#1318
0#
1%
#1319
1#
0%
#1320
0#
1%
#1321
#1322
0$
0%
#1323
#1324
#1325
1#
1$
#1326
0#
0$
#1327
1#
1%
#1328
1$
0%
#1329
0#
1%
#1330
1#
0$
#1331
0#
0%
#1332
1$
1%
#1333
0$
0%
#1334
1$
1%
#1335
1#
0$
#1336
0#
0%
#1337
#1338
#1339
1#
1$
#1340
0#
0$
#1341
#1342
1#
1$
#1343
0#
0$
#1344
#1345
1#
1%
#1346
0#
1$
#1347
0$
0%
#1348
#1349
#1350
#1351
1#
1%
#1352
0#
1$
#1353
1#
0$
#1354
#1355
1$
0%
#1356
0#
0$
#1357
1#
1$
#1358
#1359
0$
1%
#1360
0#
1$
#1361
0$
0%
#1362
#1363
1#
1$
#1364
#1365
#1366
0$
1%
#1367
1$
0%
#1368
0$
1%
#1369
0#
0%
#1370
1$
1%
#1371
1#
0%
#1372
0$
1%
#1373
0#
1$
#1374
0$
0%
#1375
1#
1%
#1376
1$
0%
#1377
0#
1%
#1378
1#
0%
#1379
0#
0$
#1380
1#
1%
#1381
#1382
0#
1$
#1383
0$
0%
#1384
1#
1%
#1385
0#
0%
#1386
1#
1%
#1387
1$
0%
#1388
0#
1%
#1389
0$
0%
#1390
1#
1$
#1391
0#
0$
#1392
1$
1%
#1393
#1394
0$
0%
#1395
1$
1%
#1396
#1397
#1398
0$
0%
#1399
1#
1%
#1400
0#
1$
#1401
#1402
1#
0%
#1403
0#
0$
#1404
#1405
#1406
1#
1$
#1407
0#
1%
#1408
0$
0%
#1409
1#
1%
#1410
1$
0%
#1411
0#
1%
#1412
0$
0%
#1413
1$
1%
#1414
#1415
1#
0$
#1416
1$
0%
#1417
0$
1%
#1418
0#
0%
#1419
#1420
1$
1%
#1421
0$
0%
#1422
1$
1%
#1423
1#
0$
#1424
#1425
0#
0%
#1426
1#
1%
#1427
0#
0%
#1428
#1429
1#
1%
#1430
0#
0%
#1431
1$
1%
#1432
1#
0$
#1433
1$
0%
#1434
0#
0$
#1435
1#
1%
#1436
#1437
0#
1$
#1438
1#
0$
#1439
#1440
0#
1$
#1441
1#
0$
#1442
0#
1$
#1443
0$
0%
#1444
1#
1$
#1445
#1446
#1447
0#
0$
#1448
1#
1%
#1449
1$
0%
#1450
0#
0$
#1451
1$
1%
#1452
0$
0%
#1453
1$
1%
#1454
#1455
#1456
#1457
1#
0$
#1458
0#
1$
#1459
1#
0%
#1460
0#
0$
#1461
1#
1$
#1462
#1463
#1464
0$
1%
#1465
0#
1$
#1466
0$
0%
#1467
1$
1%
#1468
1#
0$
#1469
0#
1$
#1470
1#
0$
#1471
0#
0%
#1472
1#
1$
#1473
0#
1%
#1474
#1475
1#
0$
#1476
#1477
1$
0%
#1478
0$
1%
#1479
0#
1$
#1480
0$
0%
#1481
1$
1%
#1482
1#
0%
#1483
0#
0$
#1484
1#
1%
#1485
1$
0%
#1486
0$
1%
#1487
#1488
1$
0%
#1489
0#
0$
#1490
1#
1$
#1491
0#
0$
#1492
1#
1%
#1493
#1494
0#
1$
#1495
1#
0%
#1496
0#
0$
#1497
1$
1%
#1498
1#
0$
#1499
#1500
0#
0%
#1501
1#
1$
#1502
0#
0$
#1503
#1504
#1505
1$
1%
#1506
1#
0$
#1507
#1508
0#
1$
#1509
#1510
0$
0%
#1511
#1512
#1513
1#
1$
#1514
0#
0$
#1515
1#
1%
#1516
1$
0%
#1517
0#
1%
#1518
1#
0$
#1519
1$
0%
#1520
0#
1%
#1521
#1522
0$
0%
#1523
1#
1%
#1524
1$
0%
#1525
#1526
#1527
0#
1%
#1528
1#
0%
#1529
0#
1%
#1530
0$
0%
#1531
1$
1%
#1532
1#
0$
#1533
0#
0%
#1534
#1535
#1536
1#
1%
#1537
1$
0%
#1538
0#
0$
#1539
1$
1%
#1540
1#
0%
#1541
#1542
#1543
0#
0$
#1544
1$
1%
#1545
0$
0%
#1546
1#
1%
#1547
#1548
0#
0%
#1549
#1550
#1551
1$
1%
#1552
1#
0%
#1553
#1554
#1555
0$
1%
#1556
0#
0%
#1557
1#
1$
#1558
0$
1%
#1559
0#
1$
#1560
1#
0$
#1561
0#
0%
#1562
1$
1%
#1563
0$
0%
#1564
1#
1%
#1565
0#
1$
#1566
1#
0$
#1567
#1568
#1569
#1570
#1571
0#
1$
#1572
0$
0%
#1573
1#
1$
#1574
0#
1%
#1575
1#
0%
#1576
#1577
#1578
0#
1%
#1579
1#
0$
#1580
1$
0%
#1581
0$
1%
#1582
#1583
0#
0%
#1584
#1585
1$
1%
#1586
0$
0%
#1587
1#
1$
#1588
0#
0$
#1589
#1590
1#
1$
#1591
0$
1%
#1592
0#
0%
#1593
1#
1$
#1594
0$
1%
#1595
1$
0%
#1596
0$
1%
#1597
#1598
#1599
0#
1$
#1600
0$
0%
#1601
1#
1%
#1602
0#
0%
#1603
1#
1$
#1604
0#
0$
#1605
1#
1$
#1606
#1607
0$
1%
#1608
#1609
1$
0%
#1610
0#
0$
#1611
1$
1%
#1612
#1613
1#
0%
#1614
#1615
#1616
0$
1%
#1617
0#
1$
#1618
#1619
0$
0%
#1620
1#
1%
#1621
1$
0%
#1622
0$
1%
#1623
#1624
0#
0%
#1625
1#
1%
#1626
0#
1$
#1627
1#
0$
#1628
#1629
0#
0%
#1630
1#
1$
#1631
0#
0$
#1632
1#
1%
#1633
1$
0%
#1634
0$
1%
#1635
1$
0%
#1636
0#
0$
#1637
1$
1%
#1638
#1639
1#
0$
#1640
1$
0%
#1641
0#
1%
#1642
#1643
1#
0%
#1644
#1645
0#
0$
#1646
#1647
1$
1%
#1648
#1649
#1650
1#
0%
#1651
0#
1%
#1652
1#
0$
#1653
0#
1$
#1654
1#
0$
#1655
#1656
1$
0%
#1657
#1658
0#
1%
#1659
1#
0%
#1660
0#
1%
#1661
1#
0%
#1662
#1663
0#
1%
#1664
1#
0%
#1665
0#
0$
#1666
1$
1%
#1667
0$
0%
#1668
1#
1%
#1669
1$
0%
#1670
0#
1%
#1671
1#
0%
#1672
0#
1%
#1673
1#
0%
#1674
0#
0$
#1675
#1676
1#
1%
#1677
#1678
#1679
#1680
1$
0%
#1681
#1682
0#
1%
#1683
1#
0$
#1684
1$
0%
#1685
0$
1%
#1686
0#
0%
#1687
1#
1%
#1688
#1689
1$
0%
#1690
0#
0$
#1691
1$
1%
#1692
#1693
1#
0%
#1694
0$
1%
#1695
0#
0%
#1696
1$
1%
#1697
0$
0%
#1698
1$
1%
#1699
#1700
#1701
1#
0$
#1702
0#
1$
#1703
1#
0%
#1704
0$
1%
#1705
#1706
0#
1$
#1707
1#
0$
#1708
0#
1$
#1709
0$
0%
#1710
1#
1%
#1711
0#
1$
#1712
1#
0$
#1713
0#
1$
#1714
0$
0%
#1715
#1716
#1717
1#
1%
#1718
#1719
#1720
0#
0%
#1721
1$
1%
#1722
1#
0$
#1723
#1724
1$
0%
#1725
0#
0$
#1726
1#
1%
#1727
0#
0%
#1728
1#
1%
#1729
1$
0%
#1730
0#
0$
#1731
1#
1%
#1732
0#
0%
#1733
1$
1%
#1734
0$
0%
#1735
1#
1$
#1736
0#
0$
#1737
#1738
1$
1%
#1739
#1740
1#
0$
#1741
#1742
0#
1$
#1743
1#
0%
#1744
0$
1%
#1745
0#
0%
#1746
#1747
#1748
1$
1%
#1749
1#
0%
#1750
#1751
0#
1%
#1752
1#
0$
#1753
1$
0%
#1754
#1755
0#
0$
#1756
1#
1$
#1757
0$
1%
#1758
#1759
#1760
0#
0%
#1761
1$
1%
#1762
#1763
1#
0$
#1764
0#
1$
#1765
1#
0%
#1766
0#
1%
#1767
#1768
1#
0$
#1769
0#
1$
#1770
1#
0$
#1771
1$
0%
#1772
0$
1%
#1773
#1774
0#
0%
#1775
1#
1$
#1776
0#
1%
#1777
0$
0%
#1778
1$
1%
#1779
1#
0$
#1780
0#
0%
#1781
1#
1%
#1782
0#
0%
#1783
1#
1$
#1784
0#
1%
#1785
#1786
1#
0$
#1787
0#
1$
#1788
#1789
1#
0%
#1790
0#
0$
#1791
#1792
#1793
1#
1%
#1794
#1795
#1796
0#
0%
#1797
#1798
#1799
#1800
1#
1%
#1801
0#
1$
#1802
0$
0%
#1803
1$
1%
#1804
#1805
0$
0%
#1806
#1807
#1808
1$
1%
#1809
#1810
1#
0%
#1811
0$
1%
#1812
0#
0%
#1813
#1814
#1815
1#
1$
#1816
#1817
0#
1%
#1818
1#
0$
#1819
0#
1$
#1820
0$
0%
#1821
1#
1%
#1822
0#
0%
#1823
#1824
1#
1%
#1825
0#
1$
#1826
#1827
1#
0$
#1828
1$
0%
#1829
0#
1%
#1830
#1831
1#
0%
#1832
0#
1%
#1833
0$
0%
#1834
1$
1%
#1835
1#
0$
#1836
1$
0%
#1837
0#
0$
#1838
1#
1%
#1839
0#
0%
#1840
#1841
1#
1%
#1842
0#
0%
#1843
1$
1%
#1844
#1845
1#
0$
#1846
0#
0%
#1847
1#
1$
#1848
#1849
#1850
0#
0$
#1851
1#
1%
#1852
1$
0%
#1853
0#
0$
#1854
1#
1%
#1855
#1856
#1857
0#
1$
#1858
1#
0%
#1859
0#
1%
#1860
#1861
1#
0$
#1862
